aiogram_prometheus/__init__.py
aiogram_prometheus/base_collector.py
aiogram_prometheus/dispatchers/__init__.py
aiogram_prometheus/dispatchers/collectors.py
aiogram_prometheus/dispatchers/middlewares.py
aiogram_prometheus/fsm/__init__.py
aiogram_prometheus/fsm/collectors.py
aiogram_prometheus/fsm/storages.py
aiogram_prometheus-0.3.0.dist-info/LICENSE
aiogram_prometheus-0.3.0.dist-info/METADATA
aiogram_prometheus-0.3.0.dist-info/WHEEL
aiogram_prometheus-0.3.0.dist-info/RECORD
