Metadata-Version: 2.1
Name: aiogram-prometheus
Version: 0.3.0
Summary: Aiogram Based Metrics Collection for Prometheus
Home-page: https://projects.rocshers.com/open-source/aiogram-prometheus
License: MIT
Keywords: aiogram,prometheus
Author: Aleksei Marusich
Author-email: aleksei.marusich@rocshers.com
Requires-Python: >=3.12,<4
Classifier: Intended Audience :: Developers
Classifier: Intended Audience :: Information Technology
Classifier: Intended Audience :: System Administrators
Classifier: License :: OSI Approved :: MIT License
Classifier: Programming Language :: Python
Classifier: Programming Language :: Python :: 3
Classifier: Programming Language :: Python :: 3.12
Classifier: Programming Language :: Python :: 3 :: Only
Classifier: Topic :: Software Development :: Libraries
Classifier: Topic :: Software Development :: Libraries :: Python Modules
Classifier: Topic :: System :: Archiving :: Packaging
Classifier: Topic :: System :: Software Distribution
Requires-Dist: aiogram (>=3,<4)
Requires-Dist: prometheus-client
Requires-Dist: prometheus-client-utils
Project-URL: Documentation, https://projects.rocshers.com/open-source/aiogram-prometheus/docs
Project-URL: Repository, https://gitlab.com/rocshers/python/aiogram-prometheus
